dhall-0.1.16.dist-info/METADATA
dhall-0.1.16.dist-info/WHEEL
dhall/__init__.pyi
dhall/__init__.py
dhall/py.typed
dhall/dhall.cpython-310-darwin.so
dhall-0.1.16.dist-info/RECORD
