Metadata-Version: 2.3
Name: dhall
Version: 0.1.16
Summary: Python bindings for dhall, a functional configuration language
Keywords: dhall,python
Home-Page: https://github.com/s-zeng/dhall-python
Author: Simon Zeng <contact@simonzeng.com>, Tristan Cacqueray <tdecacqu@redhat.com>, Matthias Endler <matthias-endler@gmx.net>
Author-email: Simon Zeng <contact@simonzeng.com>, Tristan Cacqueray <tdecacqu@redhat.com>, Matthias Endler <matthias-endler@gmx.net>
License: Apache-2.0
Project-URL: Source Code, https://github.com/s-zeng/dhall-python
